mcp_observer_server/__init__.py
mcp_observer_server/py.typed
mcp_observer_server/server.py
mcp_observer_server/watched.example.txt
iflow_mcp_mcp_observer_server-0.1.1.dist-info/METADATA
iflow_mcp_mcp_observer_server-0.1.1.dist-info/WHEEL
iflow_mcp_mcp_observer_server-0.1.1.dist-info/entry_points.txt
iflow_mcp_mcp_observer_server-0.1.1.dist-info/licenses/LICENSE
iflow_mcp_mcp_observer_server-0.1.1.dist-info/RECORD
