Metadata-Version: 2.4
Name: iflow-mcp_mcp-observer-server
Version: 0.1.1
Summary: An MCP server that monitors system events, such as file changes, and sends notifications to an MCP client
Author-email: Your Name <hesreallyhim@proton.me>
License-File: LICENSE
Requires-Python: >=3.10
Requires-Dist: anyio>=3.7.0
Requires-Dist: click>=8.1.0
Requires-Dist: mcp[cli]>=0.1.0
Requires-Dist: pydantic>=2.0.0
Requires-Dist: watchdog>=3.0.0
Provides-Extra: dev
Requires-Dist: pre-commit>=3.5.0; extra == 'dev'
Requires-Dist: pytest-asyncio>=0.21.0; extra == 'dev'
Requires-Dist: pytest-cov>=4.1.0; extra == 'dev'
Requires-Dist: pytest>=7.0.0; extra == 'dev'
Requires-Dist: ruff>=0.2.0; extra == 'dev'
